pycep/__init__.py
pycep/bicep.lark
pycep/main.py
pycep/py.typed
pycep/transformer.py
pycep/typing.py
pycep/validator.py
pycep_parser-0.4.2.dist-info/LICENSE
pycep_parser-0.4.2.dist-info/METADATA
pycep_parser-0.4.2.dist-info/WHEEL
pycep_parser-0.4.2.dist-info/RECORD
