Metadata-Version: 2.1
Name: pycep-parser
Version: 0.4.2
Summary: A Python based Bicep parser
Home-page: https://github.com/gruebel/pycep
License: Apache-2.0
Keywords: bicep,parser,lark
Author: Anton Grübel
Author-email: anton.gruebel@gmail.com
Requires-Python: >=3.7,<4.0
Classifier: License :: OSI Approved :: Apache Software License
Classifier: Programming Language :: Python :: 3
Classifier: Programming Language :: Python :: 3.7
Classifier: Programming Language :: Python :: 3.8
Classifier: Programming Language :: Python :: 3.9
Classifier: Programming Language :: Python :: 3.10
Classifier: Programming Language :: Python :: 3.11
Classifier: Programming Language :: Python :: 3 :: Only
Classifier: Programming Language :: Python :: 3.10
Classifier: Programming Language :: Python :: 3.11
Classifier: Programming Language :: Python :: 3.12
Classifier: Programming Language :: Python :: 3.7
Classifier: Programming Language :: Python :: 3.8
Classifier: Programming Language :: Python :: 3.9
Classifier: Typing :: Typed
Requires-Dist: importlib-resources (>=2.0.0) ; python_version < "3.9"
Requires-Dist: lark (>=1.1.2)
Requires-Dist: regex (>=2022.1.18)
Requires-Dist: typing-extensions (>=3.10.0)
Project-URL: Repository, https://github.com/gruebel/pycep
